{"chunk_definitions":[{"row":8,"row_count":1,"visible":true,"expansion_state":0,"options":{"engine":"r","label":"setup","include":false},"document_id":"C5E6B579","chunk_id":"csetup_chunk","chunk_label":"setup"},{"row":36,"row_count":1,"visible":true,"expansion_state":0,"options":{"engine":"r","label":"datwins","warning":false,"results":"hide"},"document_id":"C5E6B579","chunk_id":"c3votrr6cydcd","chunk_label":"datwins"},{"row":63,"row_count":1,"visible":true,"expansion_state":0,"options":{"engine":"r","label":"peso1girl","echo":false,"results":"hide"},"document_id":"C5E6B579","chunk_id":"cb02n64im0ykh","chunk_label":"peso1girl"},{"row":69,"row_count":1,"visible":true,"expansion_state":0,"options":{"engine":"r","label":"peso1girlic"},"document_id":"C5E6B579","chunk_id":"cpt6cpwbdmrso","chunk_label":"peso1girlic"},{"row":75,"row_count":1,"visible":true,"expansion_state":0,"options":{"engine":"r","label":"peso1girlic2","echo":false,"results":"hide"},"document_id":"C5E6B579","chunk_id":"c79qtb8ow073h","chunk_label":"peso1girlic2"},{"row":92,"row_count":1,"visible":true,"expansion_state":0,"options":{"engine":"r","label":"peso1girlP"},"document_id":"C5E6B579","chunk_id":"c1ffsopk693yn","chunk_label":"peso1girlP"},{"row":127,"row_count":1,"visible":true,"expansion_state":0,"options":{"engine":"r","label":"unnamed-chunk-49"},"document_id":"C5E6B579","chunk_id":"ce5u2k0oftbtf","chunk_label":"unnamed-chunk-1"},{"row":151,"row_count":1,"visible":true,"expansion_state":0,"options":{"engine":"r","label":"unnamed-chunk-50"},"document_id":"C5E6B579","chunk_id":"cwjprlnvm0066","chunk_label":"unnamed-chunk-2"},{"row":167,"row_count":1,"visible":true,"expansion_state":0,"options":{"engine":"r","label":"sgesFAC1"},"document_id":"C5E6B579","chunk_id":"cao1d9bpkzcz4","chunk_label":"sgesFAC1"}],"doc_write_time":1667393944,"working_dir":null,"chunk_rendered_width":700}